moosez/__init__.py
moosez/constants.py
moosez/download.py
moosez/file_utilities.py
moosez/image_conversion.py
moosez/image_processing.py
moosez/input_validation.py
moosez/models.py
moosez/moosez.py
moosez/predict.py
moosez/system.py
moosez/benchmarking/__init__.py
moosez/benchmarking/benchmark.py
moosez/mappings/SNOMED.py
moosez/mappings/__init__.py
moosez/nnUNet_custom_trainer/MOOSE_custom_trainers.py
moosez/nnUNet_custom_trainer/__init__.py
moosez/nnUNet_custom_trainer/utility.py
moosez-3.1.5.dist-info/licenses/LICENSE
moosez-3.1.5.dist-info/METADATA
moosez-3.1.5.dist-info/WHEEL
moosez-3.1.5.dist-info/entry_points.txt
moosez-3.1.5.dist-info/top_level.txt
moosez-3.1.5.dist-info/RECORD
