Metadata-Version: 2.4
Name: moosez
Version: 3.1.5
Summary: An AI-inference engine for 3D clinical and preclinical whole-body segmentation tasks
Author-email: Lalith Kumar Shiyam Sundar <Lalith.shiyam@med.uni-muenchen.de>, Sebastian Gutschmayer <sebastian.gutschmayer@meduniwien.ac.at>, Manuel Pires <manuel.pires@meduniwien.ac.at>
License: Apache-2.0
Keywords: moosez,model-zoo,nnUNet,medical-imaging,tumor-segmentation,organ-segmentation,bone-segmentation,lung-segmentation,muscle-segmentation,fat-segmentation,vessel-segmentation,vertebral-segmentation,rib-segmentation,preclinical-segmentation,clinical-segmentation
Classifier: Development Status :: 4 - Beta
Classifier: Intended Audience :: Developers
Classifier: Intended Audience :: Healthcare Industry
Classifier: License :: OSI Approved :: Apache Software License
Classifier: Programming Language :: Python :: 3 :: Only
Classifier: Programming Language :: Python :: 3.10
Classifier: Topic :: Scientific/Engineering :: Medical Science Apps.
Requires-Python: >=3.10
License-File: LICENSE
Requires-Dist: torch
Requires-Dist: SimpleITK
Requires-Dist: nnunetv2>=2.6.0
Requires-Dist: halo
Requires-Dist: pydicom
Requires-Dist: numpy
Requires-Dist: pyfiglet
Requires-Dist: natsort
Requires-Dist: colorama
Requires-Dist: dask
Requires-Dist: rich
Requires-Dist: pandas
Requires-Dist: dicom2nifti
Requires-Dist: emoji
Requires-Dist: matplotlib
Requires-Dist: psutil
Requires-Dist: nibabel
Dynamic: license-file
